wyn_wav2lip/__init__.py
wyn_wav2lip/easy_functions.py
wyn_wav2lip/models/__init__.py
wyn_wav2lip/models/conv.py
wyn_wav2lip/models/syncnet.py
wyn_wav2lip/models/wav2lip.py
wyn_wav2lip/wav2lip.py
wyn_wav2lip-0.2.3.dist-info/METADATA
wyn_wav2lip-0.2.3.dist-info/WHEEL
wyn_wav2lip-0.2.3.dist-info/RECORD
