Metadata-Version: 2.1
Name: wyn-wav2lip
Version: 0.2.3
Summary: A simple package to run Wav2Lip for lip synchronization with quality enhancements.
Author: Your Name
Author-email: your.email@example.com
Requires-Python: >=3.8,<4.0
Classifier: Programming Language :: Python :: 3
Classifier: Programming Language :: Python :: 3.8
Classifier: Programming Language :: Python :: 3.9
Classifier: Programming Language :: Python :: 3.10
Classifier: Programming Language :: Python :: 3.11
Classifier: Programming Language :: Python :: 3.12
Requires-Dist: basicsr (==1.4.2)
Requires-Dist: batch_face (>=1.0.4,<2.0.0)
Requires-Dist: configparser (>=5.3.0,<6.0.0)
Requires-Dist: gfpgan (>=1.3.8,<2.0.0)
Requires-Dist: torch (>=2.0,<3.0)
